checkthat_ai/__init__.py
checkthat_ai/_client.py
checkthat_ai/_exceptions.py
checkthat_ai/_types.py
checkthat_ai/_version.py
checkthat_ai/async_client.py
checkthat_ai/_utils/__init__.py
checkthat_ai/_utils/_helpers.py
checkthat_ai/resources/__init__.py
checkthat_ai/resources/chat.py
checkthat_ai/resources/models.py
checkthat_ai/resources/chat/__init__.py
checkthat_ai/resources/chat/completions/__init__.py
checkthat_ai/resources/chat/completions/completions.py
checkthat_ai/types/__init__.py
checkthat_ai/types/chat/__init__.py
checkthat_ai/types/chat/completions.py
checkthat_ai-0.2.0.dist-info/licenses/LICENSE
checkthat_ai-0.2.0.dist-info/METADATA
checkthat_ai-0.2.0.dist-info/WHEEL
checkthat_ai-0.2.0.dist-info/top_level.txt
checkthat_ai-0.2.0.dist-info/RECORD
