Metadata-Version: 2.4
Name: checkthat-ai
Version: 0.2.0
Summary: A Python SDK for the CheckThat AI platform's unified LLM API with claim refinement and normalization capabilities.
Author-email: CheckThat AI <kadapalanikhil@gmail.com>
Maintainer-email: Nikhil Kadapala <kadapalanikhil@gmail.com>
License-Expression: MIT
Project-URL: Homepage, https://checkthat-ai.com
Project-URL: Repository, https://github.com/nikhil-kadapala/checkthat-ai
Project-URL: Bug Tracker, https://github.com/nikhil-kadapala/checkthat-ai/issues
Project-URL: Documentation, https://docs.checkthat-ai.com
Project-URL: Changelog, https://github.com/nikhil-kadapala/checkthat-ai/blob/main/CHANGELOG.md
Keywords: ai,llm,fact-checking,claim-normalization,claim-refinement,structured-output,openai,anthropic,gemini,xai,together,api,sdk
Classifier: Development Status :: 4 - Beta
Classifier: Intended Audience :: Developers
Classifier: Operating System :: OS Independent
Classifier: Programming Language :: Python :: 3
Classifier: Programming Language :: Python :: 3.8
Classifier: Programming Language :: Python :: 3.9
Classifier: Programming Language :: Python :: 3.10
Classifier: Programming Language :: Python :: 3.11
Classifier: Programming Language :: Python :: 3.12
Classifier: Programming Language :: Python :: 3.13
Classifier: Topic :: Software Development :: Libraries :: Python Modules
Classifier: Topic :: Scientific/Engineering :: Artificial Intelligence
Classifier: Topic :: Internet :: WWW/HTTP :: Dynamic Content
Classifier: Topic :: Text Processing :: Linguistic
Classifier: Topic :: Software Development :: Quality Assurance
Requires-Python: >=3.8
License-File: LICENSE
Requires-Dist: openai<2.0.0,>=1.0.0
Requires-Dist: httpx<1.0.0,>=0.23.0
Requires-Dist: pydantic<3.0.0,>=2.0.0
Provides-Extra: dev
Requires-Dist: pytest>=6.0.0; extra == "dev"
Requires-Dist: pytest-cov>=4.0.0; extra == "dev"
Requires-Dist: black>=22.0.0; extra == "dev"
Requires-Dist: isort>=5.0.0; extra == "dev"
Requires-Dist: mypy>=1.0.0; extra == "dev"
Requires-Dist: flake8>=4.0.0; extra == "dev"
Dynamic: license-file
